logagg_utils/__init__.py
logagg_utils/nsqsender.py
logagg_utils/utils.py
logagg_utils-0.5.2.dist-info/LICENSE
logagg_utils-0.5.2.dist-info/METADATA
logagg_utils-0.5.2.dist-info/WHEEL
logagg_utils-0.5.2.dist-info/dependency_links.txt
logagg_utils-0.5.2.dist-info/top_level.txt
logagg_utils-0.5.2.dist-info/RECORD
